cis_checks_9/__init__.py
cis_checks_9/iam_control_1.py
cis_checks_9/logging_control_2.py
cis_checks_9/monitoring_control_3.py
cis_checks_9/networking_control_4.py
cis_checks_9/security_control_5.py
cis_checks_9/utils.py
cis_checks_9-0.0.10.dist-info/METADATA
cis_checks_9-0.0.10.dist-info/WHEEL
cis_checks_9-0.0.10.dist-info/top_level.txt
cis_checks_9-0.0.10.dist-info/RECORD
