Metadata-Version: 2.1
Name: cis_checks_9
Version: 0.0.10
Summary: Provides AWS compliance details
Author-email: "dheeraj.banodha" <dheerajmbanodha@gmail.com>
Classifier: Programming Language :: Python :: 3
Classifier: Operating System :: OS Independent
Requires-Python: >=3.7
